pytest_email/__init__.py
pytest_email/plugin.py
pytest_email-0.3.dist-info/LICENSE
pytest_email-0.3.dist-info/METADATA
pytest_email-0.3.dist-info/WHEEL
pytest_email-0.3.dist-info/entry_points.txt
pytest_email-0.3.dist-info/top_level.txt
pytest_email-0.3.dist-info/zip-safe
pytest_email-0.3.dist-info/RECORD
